Metadata-Version: 2.1
Name: cnvd-scrapy
Version: 0.1.0
Summary: cnvd_scrapy
Home-page: https://github.com/YangLuchao/CNVD_spider
Author: Awesome Soul
Author-email: www611830@163.com
License: MIT
Platform: UNKNOWN
Classifier: License :: OSI Approved :: MIT License
Classifier: Programming Language :: Python
Classifier: Programming Language :: Python :: 3
Classifier: Programming Language :: Python :: 3.6
Classifier: Programming Language :: Python :: Implementation :: CPython
Classifier: Programming Language :: Python :: Implementation :: PyPy
Requires-Python: >=3.6.0
